setup.py
reloaded_set/__init__.py
reloaded_set.egg-info/PKG-INFO
reloaded_set.egg-info/SOURCES.txt
reloaded_set.egg-info/dependency_links.txt
reloaded_set.egg-info/top_level.txt