Metadata-Version: 1.1
Name: reloaded-set
Version: 0.4
Summary: A frozenset that can reload his data.
Home-page: https://github.com/tomerghelber/reloaded-frozenset
Author: UNKNOWN
Author-email: UNKNOWN
License: BSD
Keywords: reloaded,set
Platform: UNKNOWN
Classifier: Development Status :: 5 - Production/Stable
Classifier: Intended Audience :: Developers
Classifier: Operating System :: OS Independent
Classifier: Programming Language :: Python
Classifier: Programming Language :: Python :: 3
Classifier: Programming Language :: Python :: 3.3
Classifier: Programming Language :: Python :: 3.4
Classifier: Programming Language :: Python :: Implementation
Classifier: Programming Language :: Python :: Implementation :: CPython
Classifier: Topic :: Software Development
Classifier: Topic :: Software Development :: Libraries
Classifier: Topic :: Software Development :: Libraries :: Python Modules
